zloipassgen_pkg/__init__.py
zloipassgen_pkg/zloipassgen.py
zloipassgen_pkg_Zlomorda-1.0.dist-info/LICENSE.md
zloipassgen_pkg_Zlomorda-1.0.dist-info/METADATA
zloipassgen_pkg_Zlomorda-1.0.dist-info/WHEEL
zloipassgen_pkg_Zlomorda-1.0.dist-info/top_level.txt
zloipassgen_pkg_Zlomorda-1.0.dist-info/RECORD
