Metadata-Version: 2.1
Name: zloipassgen-pkg-Zlomorda
Version: 1.0
Summary: Zloi (and Evil) password generator
Home-page: https://github.com/Zlomorda/zloipassgen
Author: Zlomorda
Author-email: daticho@gmail.com
License: UNKNOWN
Platform: UNKNOWN
Classifier: Programming Language :: Python :: 3
Classifier: License :: OSI Approved :: MIT License
Classifier: Operating System :: OS Independent
Requires-Python: >=3.6
